ChinaHolidays/ChinaHolidays.py
ChinaHolidays/__init__.py
ChinaHolidays/official_info.toml
chinaholidays-0.1.0.dist-info/licenses/LICENSE
chinaholidays-0.1.0.dist-info/METADATA
chinaholidays-0.1.0.dist-info/WHEEL
chinaholidays-0.1.0.dist-info/top_level.txt
chinaholidays-0.1.0.dist-info/RECORD
