Metadata-Version: 2.4
Name: ChinaHolidays
Version: 0.1.0
Summary: 获取中国节假日信息
License-Expression: MIT
Requires-Python: >=3.9
License-File: LICENSE
Requires-Dist: toml
Dynamic: license-file
